{
    "configurations": [
        {
            "name": "Mac",
            "includePath": [
            "${workspaceFolder}",
            "${workspaceFolder}/src",
            "${workspaceFolder}/src/core",
            "${workspaceFolder}/src/blocks",
            "${workspaceFolder}/src/levels",
            "${workspaceFolder}/src/ui",
            "${workspaceFolder}/src/utils"
            ],
            "defines": [],
            "compilerPath": "/usr/bin/clang",
            "cStandard": "c17",
            "cppStandard": "c++17",
            "intelliSenseMode": "macos-clang-arm64"
        }
    ],
    "version": 4
}